{
  "type": "FeatureCollection",
  "features": [
    {
      "type": "Feature",
      "geometry": { "type": "Point", "coordinates": [10.442, 53.277] },
      "properties": {
        "region": "Adendorf",
        "street": "Ahornweg",
        "address": "Ahornweg 1, 21365 Adendorf",
        "waste_schedules": {
          "Sperrmüll Altmetall": ["Di. 27.01.2026", "Di. 03.03.2026"],
          "Restmüll": ["Mo. 02.03.2026", "Mo. 16.03.2026"]
        }
      }
    },
    {
      "type": "Feature",
      "geometry": { "type": "Point", "coordinates": [10.455, 53.285] },
      "properties": {
        "region": "Adendorf",
        "street": "Berliner Allee",
        "address": "Berliner Allee 5, 21365 Adendorf",
        "waste_schedules": {
          "Biotonne": ["Di. 27.01.2026", "Di. 10.02.2026"],
          "Papier": ["Fr. 06.03.2026"]
        }
      }
    }
  ]
}
